gwt/__init__.py
gwt/gwt.cpython-310-darwin.so
gwt-0.1.2.dist-info/METADATA
gwt-0.1.2.dist-info/WHEEL
gwt-0.1.2.dist-info/entry_points.txt
gwt-0.1.2.dist-info/RECORD
