Metadata-Version: 2.4
Name: gwt
Version: 0.1.2
Summary: Git Worktree CLI with better DX
Author-email: waydegilliam <waydegilliam@gmail.com>
Requires-Python: >=3.10
